nonebot_plugin_netease_name/__init__.py
nonebot_plugin_netease_name/main.py
nonebot_plugin_netease_name-0.1.0.post3.dist-info/licenses/LICENSE
nonebot_plugin_netease_name-0.1.0.post3.dist-info/METADATA
nonebot_plugin_netease_name-0.1.0.post3.dist-info/WHEEL
nonebot_plugin_netease_name-0.1.0.post3.dist-info/top_level.txt
nonebot_plugin_netease_name-0.1.0.post3.dist-info/RECORD
