Metadata-Version: 2.4
Name: nonebot-plugin-netease-name
Version: 0.1.0.post3
Summary: Nonebot plugin for for generating Minecraft Netease Version nickname
Requires-Python: <4.0,>=3.10
License-File: LICENSE
Requires-Dist: nonebot-adapter-onebot>=2.4.6
Requires-Dist: nonebot-plugin-localstore>=0.7.4
Requires-Dist: nonebot2>=2.4.2
Dynamic: license-file
